README.md
setup.py
bin/completion-stackd.bash
bin/docker-stack-containers-cleanup
bin/docker-stack-rm
bin/docker-stack-volumes-cleanup
bin/portainer-stack-up
stackd/__init__.py
stackd/__main__.py
stackd/api_bash.py
stackd/api_build.py
stackd/api_bundle.py
stackd/api_cc.py
stackd/api_clear.py
stackd/api_compo.py
stackd/api_compo_freeze.py
stackd/api_config_prune.py
stackd/api_deploy.py
stackd/api_deploy_with_portainer.py
stackd/api_env.py
stackd/api_exec.py
stackd/api_getimagelist.py
stackd/api_getname.py
stackd/api_help.py
stackd/api_infos.py
stackd/api_logs.py
stackd/api_ls.py
stackd/api_ps.py
stackd/api_pull.py
stackd/api_reboot_docker.py
stackd/api_reset.py
stackd/api_rm.py
stackd/api_rm_with_portainer.py
stackd/api_sh.py
stackd/api_stacks.py
stackd/api_update.py
stackd/api_upgrade.py
stackd/api_vc.py
stackd/autocreate_networks.py
stackd/build_stack_compose_dependencies.py
stackd/build_stack_compose_file.py
stackd/build_stack_env_file.py
stackd/cmd_after_clear.py
stackd/cmd_before_clear.py
stackd/cmd_cc.py
stackd/cmd_clear.py
stackd/cmd_deploy.py
stackd/cmd_exec.py
stackd/cmd_rm.py
stackd/cmd_stacks_logs.py
stackd/cmd_stacks_rm.py
stackd/cmd_stacks_up.py
stackd/cmd_update.py
stackd/cmd_vc.py
stackd/docker_compose_config.py
stackd/flatten.py
stackd/get_required_images.py
stackd/get_template.py
stackd/load_all_build_dirs_from_env.py
stackd/load_bundle.py
stackd/load_compose.py
stackd/load_env_defaults.py
stackd/load_env_file.py
stackd/load_env_files.py
stackd/load_hash_versions.py
stackd/load_vars_data.py
stackd/load_vars_files.py
stackd/multiprocess_loop.py
stackd/parse_yaml.py
stackd/paths.py
stackd/printError.py
stackd/pull_check.py
stackd/pull_check_display_result.py
stackd/run_dir_cmd.py
stackd/run_portainer_stack_up.py
stackd/run_shell.py
stackd/services_logs.py
stackd/split_list.py
stackd/style.py
stackd/version.py
stackd/which.py
stackd.egg-info/PKG-INFO
stackd.egg-info/SOURCES.txt
stackd.egg-info/dependency_links.txt
stackd.egg-info/entry_points.txt
stackd.egg-info/requires.txt
stackd.egg-info/top_level.txt