Metadata-Version: 1.1
Name: stackd
Version: 0.94
Summary: STACKD - A docker swarm deploy helper according to environment
Home-page: https://gitlab.com/youtopia.earth/ops/stackd
Author: Idetoile
Author-email: idetoile@protonmail.com
License: MIT
Download-URL: https://gitlab.com/youtopia.earth/ops/stackd/-/archive/master/stackd-master.tar.gz
Keywords: docker,docker-stack,env
Platform: UNKNOWN
Classifier: Development Status :: 3 - Alpha
Classifier: Intended Audience :: Developers
Classifier: License :: OSI Approved :: MIT License
Classifier: Programming Language :: Python :: 3
